{"cameraMode":{"drawMode":0,"name":"Shaded","section":"Shading Mode"},"sceneLighting":true,"audioPlay":false,"sceneViewState":{"showFog":true,"showMaterialUpdate":false,"showSkybox":true,"showFlares":true,"showImageEffects":true,"showParticleSystems":true},"in2DMode":false,"pivot":{"x":2.4778451919555666,"y":7.453612804412842,"z":5.66917610168457},"rotation":{"x":0.03682772442698479,"y":0.6978058815002441,"z":0.03596711903810501,"w":-0.7144510746002197},"size":2.8578834533691408,"orthographic":false}